{"entryId": "tweet-944733364501725186", "sortIndex": "1854146985838247917", "content": {"entryType": "TimelineTimelineItem", "__typename": "TimelineTimelineItem", "itemContent": {"itemType": "TimelineTweet", "__typename": "TimelineTweet", "tweet_results": {"result": {"__typename": "Tweet", "rest_id": "944733364501725186", "core": {"user_results": {"result": {"__typename": "User", "id": "VXNlcjoxODIwODM1NA==", "rest_id": "18208354", "affiliates_highlighted_label": {}, "is_blue_verified": true, "profile_image_shape": "Circle", "legacy": {"created_at": "Thu Dec 18 04:01:47 +0000 2008", "default_profile": false, "default_profile_image": false, "description": "Stand up comic/mixed martial arts fanatic/psychedelic adventurer Host of The Joe Rogan Experience #FreakParty https://t.co/AZOVBquseu", "entities": {"description": {"urls": [{"display_url": "facebook.com/JOEROGAN", "expanded_url": "http://www.facebook.com/JOEROGAN", "url": "https://t.co/AZOVBquseu", "indices": [110, 133]}]}, "url": {"urls": [{"display_url": "joerogan.com", "expanded_url": "http://www.joerogan.com", "url": "https://t.co/OTuESddlcz", "indices": [0, 23]}]}}, "fast_followers_count": 0, "favourites_count": 886, "followers_count": 13531867, "friends_count": 3936, "has_custom_timelines": true, "is_translator": false, "listed_count": 26370, "location": "", "media_count": 4229, "name": "Joe Rogan", "normal_followers_count": 13531867, "pinned_tweet_ids_str": ["1851117181964046431"], "possibly_sensitive": false, "profile_banner_url": "https://pbs.twimg.com/profile_banners/18208354/1720977927", "profile_image_url_https": "https://pbs.twimg.com/profile_images/552307347851210752/vrXDcTFC_normal.jpeg", "profile_interstitial_type": "", "screen_name": "joerogan", "statuses_count": 45910, "translator_type": "none", "url": "https://t.co/OTuESddlcz", "verified": false, "withheld_in_countries": []}, "tipjar_settings": {"is_enabled": false, "bandcamp_handle": "", "bitcoin_handle": "", "cash_app_handle": "", "ethereum_handle": "", "gofundme_handle": "", "patreon_handle": "", "pay_pal_handle": "", "venmo_handle": ""}}}}, "unmention_data": {}, "edit_control": {"edit_tweet_ids": ["944733364501725186"], "editable_until_msecs": "1514078761051", "is_edit_eligible": true, "edits_remaining": "5"}, "is_translatable": false, "views": {"state": "Enabled"}, "source": "<a href=\"http://twitter.com/download/iphone\" rel=\"nofollow\">Twitter for iPhone</a>", "quoted_status_result": {"result": {"__typename": "Tweet", "rest_id": "944733134553219073", "core": {"user_results": {"result": {"__typename": "User", "id": "VXNlcjoxOTQwMjIzOA==", "rest_id": "19402238", "affiliates_highlighted_label": {}, "is_blue_verified": true, "profile_image_shape": "Circle", "legacy": {"created_at": "Fri Jan 23 16:56:32 +0000 2009", "default_profile": false, "default_profile_image": false, "description": "Covering the latest news in all fields of science. Publisher @society4science. See also @SN_Explores.", "entities": {"description": {"urls": []}, "url": {"urls": [{"display_url": "sciencenews.org", "expanded_url": "https://www.sciencenews.org", "url": "https://t.co/qDpSL8ca1J", "indices": [0, 23]}]}}, "fast_followers_count": 0, "favourites_count": 591, "followers_count": 5237504, "friends_count": 552, "has_custom_timelines": false, "is_translator": false, "listed_count": 19956, "location": "Washington, DC", "media_count": 11273, "name": "Science News", "normal_followers_count": 5237504, "pinned_tweet_ids_str": ["1565445141741142017"], "possibly_sensitive": false, "profile_banner_url": "https://pbs.twimg.com/profile_banners/19402238/1403559093", "profile_image_url_https": "https://pbs.twimg.com/profile_images/1210648820541018113/j4qqEa6F_normal.png", "profile_interstitial_type": "", "screen_name": "ScienceNews", "statuses_count": 75764, "translator_type": "none", "url": "https://t.co/qDpSL8ca1J", "verified": false, "withheld_in_countries": []}, "tipjar_settings": {"is_enabled": false, "bandcamp_handle": "", "bitcoin_handle": "", "cash_app_handle": "", "ethereum_handle": "", "gofundme_handle": "", "patreon_handle": "", "pay_pal_handle": "", "venmo_handle": ""}}}}, "unmention_data": {}, "edit_control": {"edit_tweet_ids": ["944733134553219073"], "editable_until_msecs": "1514078706227", "is_edit_eligible": true, "edits_remaining": "5"}, "is_translatable": false, "views": {"state": "Enabled"}, "source": "<a href=\"http://www.hootsuite.com\" rel=\"nofollow\">Hootsuite</a>", "legacy": {"bookmark_count": 0, "bookmarked": false, "created_at": "Sun Dec 24 00:55:06 +0000 2017", "conversation_id_str": "944733134553219073", "display_text_range": [0, 108], "entities": {"hashtags": [], "media": [{"display_url": "pic.x.com/BssDPTUEAE", "expanded_url": "https://x.com/ScienceNews/status/944733134553219073/photo/1", "id_str": "944733129142620166", "indices": [109, 132], "media_key": "16_944733129142620166", "media_url_https": "https://pbs.twimg.com/tweet_video_thumb/DRxdxooW0AYtLyp.jpg", "type": "animated_gif", "url": "https://t.co/BssDPTUEAE", "ext_media_availability": {"status": "Available"}, "sizes": {"large": {"h": 240, "w": 426, "resize": "fit"}, "medium": {"h": 240, "w": 426, "resize": "fit"}, "small": {"h": 240, "w": 426, "resize": "fit"}, "thumb": {"h": 150, "w": 150, "resize": "crop"}}, "original_info": {"height": 240, "width": 426, "focus_rects": []}, "video_info": {"aspect_ratio": [71, 40], "variants": [{"bitrate": 0, "content_type": "video/mp4", "url": "https://video.twimg.com/tweet_video/DRxdxooW0AYtLyp.mp4"}]}, "media_results": {"result": {"media_key": "16_944733129142620166"}}}], "symbols": [], "timestamps": [], "urls": [{"display_url": "ow.ly/tChR30hnO1e", "expanded_url": "http://ow.ly/tChR30hnO1e", "url": "https://t.co/EWtDZ6y8ye", "indices": [85, 108]}], "user_mentions": []}, "extended_entities": {"media": [{"display_url": "pic.x.com/BssDPTUEAE", "expanded_url": "https://x.com/ScienceNews/status/944733134553219073/photo/1", "id_str": "944733129142620166", "indices": [109, 132], "media_key": "16_944733129142620166", "media_url_https": "https://pbs.twimg.com/tweet_video_thumb/DRxdxooW0AYtLyp.jpg", "type": "animated_gif", "url": "https://t.co/BssDPTUEAE", "ext_media_availability": {"status": "Available"}, "sizes": {"large": {"h": 240, "w": 426, "resize": "fit"}, "medium": {"h": 240, "w": 426, "resize": "fit"}, "small": {"h": 240, "w": 426, "resize": "fit"}, "thumb": {"h": 150, "w": 150, "resize": "crop"}}, "original_info": {"height": 240, "width": 426, "focus_rects": []}, "video_info": {"aspect_ratio": [71, 40], "variants": [{"bitrate": 0, "content_type": "video/mp4", "url": "https://video.twimg.com/tweet_video/DRxdxooW0AYtLyp.mp4"}]}, "media_results": {"result": {"media_key": "16_944733129142620166"}}}]}, "favorite_count": 3601, "favorited": false, "full_text": "This robot can do push-ups. It even 'sweats' to keep the motors of its muscles cool. https://t.co/EWtDZ6y8ye https://t.co/BssDPTUEAE", "is_quote_status": false, "lang": "en", "possibly_sensitive": false, "possibly_sensitive_editable": true, "quote_count": 2711, "reply_count": 395, "retweet_count": 1363, "retweeted": false, "user_id_str": "19402238", "id_str": "944733134553219073"}}}, "legacy": {"bookmark_count": 5, "bookmarked": false, "created_at": "Sun Dec 24 00:56:01 +0000 2017", "conversation_id_str": "944733364501725186", "display_text_range": [0, 17], "entities": {"hashtags": [], "symbols": [], "timestamps": [], "urls": [{"display_url": "x.com/sciencenews/st\u2026", "expanded_url": "https://x.com/sciencenews/status/944733134553219073", "url": "https://t.co/ajK5XyDtgQ", "indices": [18, 41]}], "user_mentions": []}, "favorite_count": 95032, "favorited": false, "full_text": "We are so fucked. https://t.co/ajK5XyDtgQ", "is_quote_status": true, "lang": "en", "possibly_sensitive": false, "possibly_sensitive_editable": true, "quote_count": 576, "quoted_status_id_str": "944733134553219073", "quoted_status_permalink": {"url": "https://t.co/ajK5XyDtgQ", "expanded": "https://twitter.com/sciencenews/status/944733134553219073", "display": "x.com/sciencenews/st\u2026"}, "reply_count": 978, "retweet_count": 27854, "retweeted": false, "user_id_str": "18208354", "id_str": "944733364501725186"}, "quick_promote_eligibility": {"eligibility": "IneligibleUserUnauthorized"}}}, "tweetDisplayType": "Tweet"}, "clientEventInfo": {"component": "profile_best_highlights", "element": "tweet"}}}